[
    {
        "title": "Профиль",
        "icon": "person",
        "route": "/cabinet",
        "children":[
            {
                "title": "Избранное",              
                "icon": "star",
                "route": "/cabinet/favorites"
            },
            {
                "title": "Уведомления",               
                "icon": "notifications",
                "route": "/cabinet/notifications"
            },
            {
                "title": "Настройки",               
                "icon": "settings",
                "route": "/cabinet/settings"
            }
        ]
    },
    {
        "title": "Мероприятия",       
        "icon": "newspaper",
        "route": "/cabinet/events",
        "children":[
            {
                "title": "Все",              
                "icon": "list",
                "route": "/cabinet/events"
            },
            {
                "title": "Создать",              
                "icon": "add-circle",
                "route": "/cabinet/events/create"
            }
        ]
    },
    {
        
        "title": "Выход",       
        "icon": "log-out",
        "route": "/logout"
    }
    
]